crosswalk/__init__.py
crosswalk_client/__init__.py
crosswalk_client/decorators.py
crosswalk_client/encoder.py
crosswalk_client/exceptions.py
crosswalk_client/test_lib.py
crosswalk_client/methods/__init__.py
crosswalk_client/methods/client/__init__.py
crosswalk_client/methods/client/client_check.py
crosswalk_client/methods/client/set_domain.py
crosswalk_client/methods/client/set_scorer.py
crosswalk_client/methods/client/set_threshold.py
crosswalk_client/methods/domain/__init__.py
crosswalk_client/methods/domain/create_domain.py
crosswalk_client/methods/domain/delete_domain.py
crosswalk_client/methods/domain/get_domain.py
crosswalk_client/methods/domain/get_domains.py
crosswalk_client/methods/domain/update_domain.py
crosswalk_client/methods/entity/__init__.py
crosswalk_client/methods/entity/alias_by_id.py
crosswalk_client/methods/entity/alias_or_create.py
crosswalk_client/methods/entity/best_match.py
crosswalk_client/methods/entity/best_match_or_create.py
crosswalk_client/methods/entity/bulk_create.py
crosswalk_client/methods/entity/create.py
crosswalk_client/methods/entity/delete_by_id.py
crosswalk_client/methods/entity/delete_match.py
crosswalk_client/methods/entity/get_entities.py
crosswalk_client/methods/entity/get_entity.py
crosswalk_client/methods/entity/match.py
crosswalk_client/methods/entity/match_or_create.py
crosswalk_client/methods/entity/supersede_by_id.py
crosswalk_client/methods/entity/update_by_id.py
crosswalk_client/methods/entity/update_match.py
crosswalk_client/objects/__init__.py
crosswalk_client/objects/domain.py
crosswalk_client/objects/entity.py
crosswalk_client/tests/__init__.py
crosswalk_client/tests/test_client_config.py
crosswalk_client/tests/test_client_domain_methods.py
crosswalk_client/tests/test_client_entity_methods.py
crosswalk_client/tests/test_domain_object_methods.py
crosswalk_client/tests/test_entity_object_methods.py
crosswalk_client/tests/test_validation_decorators.py
crosswalk_client/validators/__init__.py
django_crosswalk_client-0.0.15.dist-info/LICENSE
django_crosswalk_client-0.0.15.dist-info/METADATA
django_crosswalk_client-0.0.15.dist-info/WHEEL
django_crosswalk_client-0.0.15.dist-info/top_level.txt
django_crosswalk_client-0.0.15.dist-info/RECORD
